Metadata-Version: 1.1
Name: tabkit3
Version: 0.8.0
Summary: Coreutils-like kit for headed tab-separated files processing
Home-page: https://github.com/zaabjuda/tabkit3
Author: Dmitriy Zhiltsov
Author-email: dzhiltsov@me.com
License: PSF
Platform: UNKNOWN
Classifier: Intended Audience :: Developers
Classifier: License :: OSI Approved :: MIT License
Classifier: Programming Language :: Python
Classifier: Topic :: Software Development :: Libraries :: Python Modules
Classifier: Programming Language :: Python :: 3 :: Only
